syndb_api_client/__init__.py
syndb_api_client/api_client.py
syndb_api_client/api_response.py
syndb_api_client/configuration.py
syndb_api_client/exceptions.py
syndb_api_client/py.typed
syndb_api_client/rest.py
syndb_api_client/api/__init__.py
syndb_api_client/api/auth_api.py
syndb_api_client/api/benchmark_api.py
syndb_api_client/api/cilogon_api.py
syndb_api_client/api/dataset_api.py
syndb_api_client/api/default_api.py
syndb_api_client/api/external_api.py
syndb_api_client/api/github_api.py
syndb_api_client/api/google_api.py
syndb_api_client/api/io_api.py
syndb_api_client/api/metadata_api.py
syndb_api_client/api/neurodata_api.py
syndb_api_client/api/oauth_api.py
syndb_api_client/api/orcid_api.py
syndb_api_client/api/tag_api.py
syndb_api_client/api/user_api.py
syndb_api_client/models/__init__.py
syndb_api_client/models/animal_model_create.py
syndb_api_client/models/bearer_response.py
syndb_api_client/models/body_verify_request_token_user_auth_request_verify_token_post.py
syndb_api_client/models/body_verify_verify_user_auth_verify_post.py
syndb_api_client/models/brain_region_create_read_input.py
syndb_api_client/models/brain_region_create_read_output.py
syndb_api_client/models/brain_region_read.py
syndb_api_client/models/brain_regions_to_dataset_response.py
syndb_api_client/models/create_dataset_collection_multi_brain_region.py
syndb_api_client/models/create_read_dataset_collection_model.py
syndb_api_client/models/cultural_model_animal_name.py
syndb_api_client/models/data_license.py
syndb_api_client/models/dataset_error_detail.py
syndb_api_client/models/dataset_error_model.py
syndb_api_client/models/dataset_filter_schema.py
syndb_api_client/models/dataset_id2_syndb_tables.py
syndb_api_client/models/dataset_search_result_schema.py
syndb_api_client/models/dataset_tag_search_schema.py
syndb_api_client/models/dataset_upload_benchmark_result_schema.py
syndb_api_client/models/dataset_upload_benchmark_results_schema.py
syndb_api_client/models/detail.py
syndb_api_client-0.7.2.dist-info/METADATA
syndb_api_client-0.7.2.dist-info/WHEEL
syndb_api_client-0.7.2.dist-info/top_level.txt
syndb_api_client-0.7.2.dist-info/RECORD
