Metadata-Version: 2.2
Name: syndb_api_client
Version: 0.7.2
Summary: Synapse DB
Author-email: OpenAPI Generator Community <team@openapitools.org>
Project-URL: Repository, https://github.com/GIT_USER_ID/GIT_REPO_ID
Keywords: OpenAPI,OpenAPI-Generator,Synapse DB
Classifier: License :: OSI Approved :: GNU General Public License v2 (GPLv2)
Requires-Python: ~=3.8
Requires-Dist: urllib3<3.0.0,>=1.25.3
Requires-Dist: python-dateutil>=2.8.2
Requires-Dist: pydantic>=2
Requires-Dist: typing-extensions>=4.7.1
